<?xml version="1.0" encoding="utf-8"?>
<Memory DefaultPicturePath="Default.png">
  <Karte Id="1" Path="01_02.png">
    <Match IdRef="2" />
  </Karte>
  <Karte Id="2" Path="02_01.png">
    <Match IdRef="1" />
  </Karte>
  <Karte Id="3" Path="03_04.png">
    <Match IdRef="4" />
  </Karte>
  <Karte Id="4" Path="04_03.png">
    <Match IdRef="3" />
  </Karte>
  <Karte Id="5" Path="05_06.png">
    <Match IdRef="6" />
  </Karte>
  <Karte Id="6" Path="06_05.png">
    <Match IdRef="5" />
  </Karte>
  <Karte Id="7" Path="07_08.png">
    <Match IdRef="8" />
  </Karte>
  <Karte Id="8" Path="08_07.png">
    <Match IdRef="7" />
  </Karte>
  <Karte Id="9" Path="09_10.png">
    <Match IdRef="10" />
  </Karte>
  <Karte Id="10" Path="10_09.png">
    <Match IdRef="9" />
  </Karte>
  <Karte Id="11" Path="11_12.png">
    <Match IdRef="12" />
  </Karte>
  <Karte Id="12" Path="12_11.png">
    <Match IdRef="11" />
  </Karte>
  <Karte Id="13" Path="13_14.png">
    <Match IdRef="14" />
  </Karte>
  <Karte Id="14" Path="14_13.png">
    <Match IdRef="13" />
  </Karte>
  <Karte Id="15" Path="15_16.png">
    <Match IdRef="16" />
  </Karte>
  <Karte Id="16" Path="16_15.png">
    <Match IdRef="15" />
  </Karte>
  <Karte Id="17" Path="17_18.png">
    <Match IdRef="18" />
  </Karte>
  <Karte Id="18" Path="18_17.png">
    <Match IdRef="17" />
  </Karte>
  <Karte Id="19" Path="19_20.png">
    <Match IdRef="20" />
  </Karte>
  <Karte Id="20" Path="20_19.png">
    <Match IdRef="19" />
  </Karte>
  <Karte Id="21" Path="21_22-24.png">
    <Match IdRef="22" />
    <Match IdRef="24" />
  </Karte>
  <Karte Id="22" Path="22_21-23.png">
    <Match IdRef="21" />
    <Match IdRef="23" />
  </Karte>
  <Karte Id="23" Path="23_22-24.png">
    <Match IdRef="22" />
    <Match IdRef="24" />
  </Karte>
  <Karte Id="24" Path="24_21-23.png">
    <Match IdRef="21" />
    <Match IdRef="23" />
  </Karte>
  <Karte Id="25" Path="25_26-28.png">
    <Match IdRef="26" />
    <Match IdRef="28" />
  </Karte>
  <Karte Id="26" Path="26_25-27.png">
    <Match IdRef="25" />
    <Match IdRef="27" />
  </Karte>
  <Karte Id="27" Path="27_26-28.png">
    <Match IdRef="26" />
    <Match IdRef="28" />
  </Karte>
  <Karte Id="28" Path="28_25-27.png">
    <Match IdRef="25" />
    <Match IdRef="27" />
  </Karte>
  <Karte Id="29" Path="29_30-32.png">
    <Match IdRef="30" />
    <Match IdRef="32" />
  </Karte>
  <Karte Id="30" Path="30_29-31.png">
    <Match IdRef="29" />
    <Match IdRef="31" />
  </Karte>
  <Karte Id="31" Path="31_30-32.png">
    <Match IdRef="30" />
    <Match IdRef="32" />
  </Karte>
  <Karte Id="32" Path="32_29-31.png">
    <Match IdRef="29" />
    <Match IdRef="31" />
  </Karte>
  <Karte Id="33" Path="33_34-36.png">
    <Match IdRef="34" />
    <Match IdRef="36" />
  </Karte>
  <Karte Id="34" Path="34_33-35.png">
    <Match IdRef="33" />
    <Match IdRef="35" />
  </Karte>
  <Karte Id="35" Path="35_34-36.png">
    <Match IdRef="34" />
    <Match IdRef="36" />
  </Karte>
  <Karte Id="36" Path="36_33-35.png">
    <Match IdRef="33" />
    <Match IdRef="35" />
  </Karte>
</Memory>